optim_sentence_transformers/__init__.py
optim_sentence_transformers/optim_sentence_transformers.py
optim_sentence_transformrs-0.1.dist-info/METADATA
optim_sentence_transformrs-0.1.dist-info/WHEEL
optim_sentence_transformrs-0.1.dist-info/top_level.txt
optim_sentence_transformrs-0.1.dist-info/RECORD
